{
  "parent": "minecraft:recipes/root",
  "rewards": {
    "recipes": [
      "midnight:nightshroom_powder_from_double"
    ]
  },
  "criteria": {
    "has_fungi": {
      "trigger": "minecraft:inventory_changed",
      "conditions": {
        "items": [
          {
            "tag": "midnight:nightshroom"
          }
        ]
      }
    },
    "has_the_recipe": {
      "trigger": "minecraft:recipe_unlocked",
      "conditions": {
        "recipe": "midnight:nightshroom_powder_from_double"
      }
    }
  },
  "requirements": [
    [
      "has_fungi",
      "has_the_recipe"
    ]
  ]
}