{
  "parent": "minecraft:recipes/root",
  "rewards": {
    "recipes": [
      "midnight:tenebrum_ingot_from_blasting"
    ]
  },
  "criteria": {
    "has_ore": {
      "trigger": "minecraft:inventory_changed",
      "conditions": {
        "items": [
          {
            "item": "midnight:tenebrum_ore"
          }
        ]
      }
    },
    "has_the_recipe": {
      "trigger": "minecraft:recipe_unlocked",
      "conditions": {
        "recipe": "midnight:tenebrum_ingot_from_blasting"
      }
    }
  },
  "requirements": [
    [
      "has_ore",
      "has_the_recipe"
    ]
  ]
}